[{"allDeclaredConstructors":true,"name":"com.arjuna.ats.internal.arjuna.objectstore.jdbc.drivers.ibm_driver"},{"allDeclaredConstructors":true,"name":"com.arjuna.ats.internal.arjuna.objectstore.jdbc.drivers.jconnect_driver"},{"allDeclaredConstructors":true,"name":"com.arjuna.ats.internal.arjuna.objectstore.jdbc.drivers.h2_driver"},{"allDeclaredConstructors":true,"name":"com.arjuna.ats.internal.arjuna.objectstore.jdbc.drivers.oracle_driver"},{"allDeclaredConstructors":true,"name":"com.arjuna.ats.internal.arjuna.objectstore.jdbc.drivers.microsoft_driver"},{"allDeclaredConstructors":true,"name":"com.arjuna.ats.internal.arjuna.objectstore.jdbc.drivers.mysql_ab_driver"},{"allDeclaredConstructors":true,"name":"com.arjuna.ats.internal.arjuna.objectstore.jdbc.drivers.mysql_driver"},{"allDeclaredConstructors":true,"name":"com.arjuna.ats.internal.arjuna.objectstore.jdbc.drivers.enterprisedb_driver"},{"allDeclaredConstructors":true,"name":"com.arjuna.ats.internal.arjuna.objectstore.jdbc.drivers.postgresql_driver"},{"allDeclaredConstructors":true,"name":"com.arjuna.ats.internal.arjuna.objectstore.jdbc.drivers.mariadb_driver"},{"allDeclaredConstructors":true,"name":"com.arjuna.ats.internal.arjuna.objectstore.jdbc.drivers.edb_driver"},{"allDeclaredConstructors":true,"name":"com.arjuna.ats.internal.arjuna.objectstore.jdbc.drivers.postgres_driver"},{"allDeclaredConstructors":true,"allPublicConstructors":true,"name":"com.arjuna.ats.jta.common.JTAEnvironmentBean"},{"allDeclaredConstructors":true,"allPublicConstructors":true,"name":"com.arjuna.ats.internal.jta.transaction.arjunacore.UserTransactionImple"},{"allDeclaredConstructors":true,"allPublicConstructors":true,"name":"com.arjuna.ats.internal.arjuna.coordinator.CheckedActionFactoryImple"},{"allDeclaredConstructors":true,"allPublicConstructors":true,"name":"com.arjuna.ats.internal.jta.transaction.arjunacore.TransactionManagerImple"},{"allDeclaredConstructors":true,"allPublicConstructors":true,"name":"com.arjuna.ats.internal.jta.transaction.arjunacore.TransactionSynchronizationRegistryImple"},{"allDeclaredConstructors":true,"allPublicConstructors":true,"name":"com.arjuna.ats.arjuna.common.ObjectStoreEnvironmentBean"},{"allDeclaredConstructors":true,"allPublicConstructors":true,"name":"com.arjuna.ats.internal.arjuna.objectstore.ShadowNoFileLockStore"},{"allDeclaredConstructors":true,"allPublicConstructors":true,"name":"com.arjuna.ats.internal.arjuna.objectstore.jdbc.JDBCStore"},{"allDeclaredConstructors":true,"allPublicConstructors":true,"name":"com.arjuna.ats.internal.arjuna.utils.SocketProcessId"},{"allDeclaredConstructors":true,"allPublicConstructors":true,"name":"com.arjuna.ats.internal.arjuna.recovery.AtomicActionRecoveryModule"},{"allDeclaredConstructors":true,"allPublicConstructors":true,"name":"com.arjuna.ats.internal.jta.recovery.arjunacore.XARecoveryModule"},{"allDeclaredConstructors":true,"allPublicConstructors":true,"name":"com.arjuna.ats.internal.jta.resources.arjunacore.XAResourceRecord"},{"allDeclaredConstructors":true,"allPublicConstructors":true,"name":"com.arjuna.ats.internal.jta.recovery.arjunacore.JTATransactionLogXAResourceOrphanFilter"},{"allDeclaredConstructors":true,"allPublicConstructors":true,"name":"com.arjuna.ats.internal.jta.recovery.arjunacore.JTANodeNameXAResourceOrphanFilter"},{"allDeclaredConstructors":true,"allPublicConstructors":true,"name":"com.arjuna.ats.internal.jta.recovery.arjunacore.JTAActionStatusServiceXAResourceOrphanFilter"},{"allDeclaredConstructors":true,"allPublicConstructors":true,"name":"com.arjuna.ats.internal.arjuna.recovery.ExpiredTransactionStatusManagerScanner"},{"allDeclaredConstructors":true,"name":"io.quarkus.runner.ApplicationImpl","fields":[{"name":"__QUARKUS_ANALYTICS_QUARKUS_VERSION"}]},{"allDeclaredConstructors":true,"name":"java.util.ArrayList"},{"allDeclaredConstructors":true,"name":"java.util.HashMap"},{"allDeclaredConstructors":true,"name":"java.util.HashSet"},{"allDeclaredConstructors":true,"name":"java.util.LinkedList"},{"allDeclaredConstructors":true,"name":"java.util.LinkedHashMap"},{"allDeclaredConstructors":true,"name":"java.util.LinkedHashSet"},{"allDeclaredConstructors":true,"name":"java.util.TreeMap"},{"allDeclaredConstructors":true,"name":"java.util.TreeSet"},{"allDeclaredConstructors":true,"name":"jakarta.ws.rs.core.Cookie","allDeclaredMethods":true},{"allDeclaredConstructors":true,"name":"io.quarkus.vertx.core.runtime.VertxLogDelegateFactory","allDeclaredMethods":true},{"allDeclaredConstructors":true,"name":"io.quarkus.vertx.mdc.provider.LateBoundMDCProvider","allDeclaredMethods":true,"allDeclaredFields":true},{"allDeclaredConstructors":true,"name":"com.mongodb.client.model.changestream.ChangeStreamDocument","allDeclaredMethods":true,"allDeclaredFields":true},{"allDeclaredConstructors":true,"name":"com.mongodb.client.model.changestream.UpdateDescription","allDeclaredMethods":true},{"allDeclaredConstructors":true,"name":"org.bson.types.ObjectId","allDeclaredMethods":true,"allDeclaredFields":true},{"allDeclaredConstructors":true,"name":"io.smallrye.mutiny.vertx.core.AbstractVerticle"},{"allDeclaredConstructors":true,"name":"io.quarkus.mongodb.runtime.dns.MongoDnsClientProvider","allDeclaredMethods":true,"allDeclaredFields":true},{"allDeclaredConstructors":true,"name":"io.quarkus.mongodb.runtime.dns.MongoDnsClient","allDeclaredMethods":true,"allDeclaredFields":true},{"allDeclaredConstructors":true,"name":"io.quarkus.resteasy.reactive.server.runtime.exceptionmappers.AuthenticationCompletionExceptionMapper"},{"allDeclaredConstructors":true,"name":"io.quarkus.resteasy.reactive.server.runtime.exceptionmappers.AuthenticationRedirectExceptionMapper"},{"allDeclaredConstructors":true,"name":"io.quarkus.resteasy.reactive.server.runtime.exceptionmappers.ForbiddenExceptionMapper"},{"allDeclaredConstructors":true,"name":"io.quarkus.resteasy.reactive.jackson.runtime.mappers.BuiltinMismatchedInputExceptionMapper"},{"allDeclaredConstructors":true,"name":"io.quarkus.resteasy.reactive.server.runtime.exceptionmappers.AuthenticationFailedExceptionMapper$ExceptionMapper$c2c34c033791b6e419bbd19d3b82f053d38098b8"},{"allDeclaredConstructors":true,"name":"io.quarkus.resteasy.reactive.server.runtime.exceptionmappers.UnauthorizedExceptionMapper$ExceptionMapper$965510594634d484a005e8aaae2361e9c9c1ea07"},{"allDeclaredConstructors":true,"name":"io.quarkus.resteasy.reactive.jackson.runtime.mappers.NativeInvalidDefinitionExceptionMapper$ExceptionMapper$9b3903a6623e908ff3590aef8cbd6d07435aea0c"},{"allDeclaredConstructors":true,"name":"com.fasterxml.jackson.databind.ser.std.SqlDateSerializer","allDeclaredMethods":true},{"allDeclaredConstructors":true,"name":"com.fasterxml.jackson.databind.ser.std.SqlTimeSerializer","allDeclaredMethods":true},{"allDeclaredConstructors":true,"name":"com.fasterxml.jackson.databind.deser.std.DateDeserializers$SqlDateDeserializer","allDeclaredMethods":true},{"allDeclaredConstructors":true,"name":"com.fasterxml.jackson.databind.deser.std.DateDeserializers$TimestampDeserializer","allDeclaredMethods":true},{"allDeclaredConstructors":true,"name":"com.fasterxml.jackson.annotation.SimpleObjectIdResolver","allDeclaredMethods":true},{"allDeclaredConstructors":true,"name":"com.fasterxml.jackson.databind.ser.std.ClassSerializer"},{"allDeclaredConstructors":true,"name":"com.fasterxml.jackson.databind.ext.CoreXMLSerializers"},{"allDeclaredConstructors":true,"name":"com.fasterxml.jackson.databind.ext.CoreXMLDeserializers"},{"allDeclaredConstructors":true,"name":"io.vertx.ext.mail.impl.sasl.AuthCram","allDeclaredMethods":true,"allDeclaredFields":true},{"allDeclaredConstructors":true,"name":"io.vertx.ext.mail.impl.sasl.AuthDigest","allDeclaredMethods":true,"allDeclaredFields":true},{"allDeclaredConstructors":true,"name":"io.vertx.ext.mail.impl.sasl.AuthLogin","allDeclaredMethods":true,"allDeclaredFields":true},{"allDeclaredConstructors":true,"name":"io.vertx.ext.mail.impl.sasl.AuthPlain","allDeclaredMethods":true,"allDeclaredFields":true},{"allDeclaredConstructors":true,"name":"io.netty.channel.socket.nio.NioSocketChannel"},{"allDeclaredConstructors":true,"name":"io.netty.channel.socket.nio.NioServerSocketChannel"},{"allDeclaredConstructors":true,"name":"io.netty.channel.socket.nio.NioDatagramChannel"},{"allDeclaredConstructors":true,"name":"sun.nio.ch.SelectorImpl","allDeclaredMethods":true,"allDeclaredFields":true},{"allDeclaredConstructors":true,"name":"io.quarkus.jackson.runtime.JacksonBuildTimeConfig$$CMImpl","allDeclaredMethods":true},{"allDeclaredConstructors":true,"name":"java.lang.String","allDeclaredMethods":true},{"allDeclaredConstructors":true,"name":"com.fasterxml.jackson.annotation.JsonInclude$Include","allDeclaredMethods":true},{"allDeclaredConstructors":true,"name":"java.time.ZoneId","allDeclaredMethods":true},{"allDeclaredConstructors":true,"name":"io.quarkus.runtime.ApplicationConfig$$CMImpl","allDeclaredMethods":true},{"allDeclaredConstructors":true,"name":"io.quarkus.runtime.BuildAnalyticsConfig$$CMImpl","allDeclaredMethods":true},{"allDeclaredConstructors":true,"name":"java.lang.Boolean","allDeclaredMethods":true},{"allDeclaredConstructors":true,"name":"java.lang.Integer","allDeclaredMethods":true},{"allDeclaredConstructors":true,"name":"io.quarkus.runtime.LiveReloadConfig$$CMImpl","allDeclaredMethods":true},{"allDeclaredConstructors":true,"name":"java.time.Duration","allDeclaredMethods":true},{"allDeclaredConstructors":true,"name":"io.quarkus.runtime.LocalesBuildTimeConfig$$CMImpl","allDeclaredMethods":true},{"allDeclaredConstructors":true,"name":"java.util.Locale","allDeclaredMethods":true},{"allDeclaredConstructors":true,"name":"io.quarkus.runtime.logging.LogBuildTimeConfig$$CMImpl","allDeclaredMethods":true},{"allDeclaredConstructors":true,"name":"io.quarkus.runtime.logging.LevelConverter","queriedMethods":[{"parameterTypes":[],"name":"provider"}]},{"allDeclaredConstructors":true,"name":"io.quarkus.runtime.logging.LogBuildTimeConfig$CategoryBuildTimeConfig$$CMImpl","allDeclaredMethods":true},{"allDeclaredConstructors":true,"name":"io.quarkus.runtime.logging.InheritableLevel","allDeclaredMethods":true},{"allDeclaredConstructors":true,"name":"io.quarkus.resteasy.reactive.common.runtime.ResteasyReactiveConfig$$CMImpl","allDeclaredMethods":true},{"allDeclaredConstructors":true,"name":"io.quarkus.runtime.configuration.MemorySize","allDeclaredMethods":true},{"allDeclaredConstructors":true,"name":"io.quarkus.resteasy.reactive.common.runtime.ResteasyReactiveConfig$ExceptionMappingConfig$$CMImpl","allDeclaredMethods":true},{"allDeclaredConstructors":true,"name":"io.quarkus.vertx.http.runtime.VertxHttpBuildTimeConfig$$CMImpl","allDeclaredMethods":true},{"allDeclaredConstructors":true,"name":"java.util.OptionalInt","allDeclaredMethods":true},{"allDeclaredConstructors":true,"name":"io.quarkus.runtime.configuration.NormalizeRootHttpPathConverter"},{"allDeclaredConstructors":true,"name":"io.vertx.core.http.ClientAuth","allDeclaredMethods":true},{"allDeclaredConstructors":true,"name":"io.quarkus.vertx.http.runtime.AuthConfig$$CMImpl","allDeclaredMethods":true},{"allDeclaredConstructors":true,"name":"io.quarkus.vertx.http.runtime.HttpStaticDirConfig$$CMImpl","allDeclaredMethods":true},{"allDeclaredConstructors":true,"name":"io.quarkus.vertx.http.runtime.management.ManagementInterfaceBuildTimeConfig$$CMImpl","allDeclaredMethods":true},{"allDeclaredConstructors":true,"name":"io.quarkus.vertx.http.runtime.management.ManagementAuthConfig$$CMImpl","allDeclaredMethods":true},{"allDeclaredConstructors":true,"name":"io.quarkus.virtual.threads.VirtualThreadsConfig$$CMImpl","allDeclaredMethods":true},{"allDeclaredConstructors":true,"name":"io.quarkus.scheduler.runtime.SchedulerConfig$$CMImpl","allDeclaredMethods":true},{"allDeclaredConstructors":true,"name":"com.cronutils.model.CronType","allDeclaredMethods":true},{"allDeclaredConstructors":true,"name":"io.quarkus.mailer.runtime.MailersBuildTimeConfig$$CMImpl","allDeclaredMethods":true},{"allDeclaredConstructors":true,"name":"io.quarkus.qute.runtime.QuteConfig$$CMImpl","allDeclaredMethods":true},{"allDeclaredConstructors":true,"name":"java.nio.charset.Charset","allDeclaredMethods":true},{"allDeclaredConstructors":true,"name":"io.quarkus.qute.runtime.QuteConfig$DuplicitTemplatesStrategy","allDeclaredMethods":true},{"allDeclaredConstructors":true,"name":"java.util.regex.Pattern","allDeclaredMethods":true},{"allDeclaredConstructors":true,"name":"io.quarkus.qute.runtime.debug.QuteDebugConfig$$CMImpl","allDeclaredMethods":true},{"allDeclaredConstructors":true,"name":"io.quarkus.qute.runtime.QuteDevModeConfig$$CMImpl","allDeclaredMethods":true},{"allDeclaredConstructors":true,"name":"io.quarkus.qute.runtime.QuteTestModeConfig$$CMImpl","allDeclaredMethods":true},{"allDeclaredConstructors":true,"name":"io.quarkus.runtime.BannerRuntimeConfig$$CMImpl","allDeclaredMethods":true},{"allDeclaredConstructors":true,"name":"io.quarkus.runtime.BuilderConfig$$CMImpl","allDeclaredMethods":true},{"allDeclaredConstructors":true,"name":"io.quarkus.runtime.BuilderConfig$Metrics$$CMImpl","allDeclaredMethods":true},{"allDeclaredConstructors":true,"name":"io.quarkus.runtime.CommandLineRuntimeConfig$$CMImpl","allDeclaredMethods":true},{"allDeclaredConstructors":true,"name":"io.quarkus.runtime.ConfigConfig$$CMImpl","allDeclaredMethods":true},{"allDeclaredConstructors":true,"name":"io.quarkus.runtime.ConfigConfig$BuildTimeMismatchAtRuntime","allDeclaredMethods":true},{"allDeclaredConstructors":true,"name":"java.net.URI","allDeclaredMethods":true},{"allDeclaredConstructors":true,"name":"io.quarkus.runtime.DebugRuntimeConfig$$CMImpl","allDeclaredMethods":true},{"allDeclaredConstructors":true,"name":"io.quarkus.runtime.LaunchConfig$$CMImpl","allDeclaredMethods":true},{"allDeclaredConstructors":true,"name":"io.quarkus.runtime.ThreadPoolConfig$$CMImpl","allDeclaredMethods":true},{"allDeclaredConstructors":true,"name":"io.quarkus.runtime.console.ConsoleRuntimeConfig$$CMImpl","allDeclaredMethods":true},{"allDeclaredConstructors":true,"name":"io.quarkus.runtime.init.InitRuntimeConfig$$CMImpl","allDeclaredMethods":true},{"allDeclaredConstructors":true,"name":"io.quarkus.runtime.init.InitRuntimeConfig$BooleanConverter"},{"allDeclaredConstructors":true,"name":"io.quarkus.runtime.logging.LogRuntimeConfig$$CMImpl","allDeclaredMethods":true},{"allDeclaredConstructors":true,"name":"io.quarkus.runtime.logging.LogRuntimeConfig$CategoryConfig$$CMImpl","allDeclaredMethods":true},{"allDeclaredConstructors":true,"name":"io.quarkus.runtime.logging.LogRuntimeConfig$ConsoleConfig$$CMImpl","allDeclaredMethods":true},{"allDeclaredConstructors":true,"name":"io.quarkus.runtime.logging.LogRuntimeConfig$AsyncConfig$$CMImpl","allDeclaredMethods":true},{"allDeclaredConstructors":true,"name":"org.jboss.logmanager.handlers.AsyncHandler$OverflowAction","allDeclaredMethods":true},{"allDeclaredConstructors":true,"name":"io.quarkus.runtime.logging.LogRuntimeConfig$FileConfig$$CMImpl","allDeclaredMethods":true},{"allDeclaredConstructors":true,"name":"io.quarkus.runtime.configuration.CharsetConverter","queriedMethods":[{"parameterTypes":[],"name":"provider"}]},{"allDeclaredConstructors":true,"name":"java.io.File","allDeclaredMethods":true},{"allDeclaredConstructors":true,"name":"io.quarkus.runtime.logging.LogRuntimeConfig$FileConfig$RotationConfig$$CMImpl","allDeclaredMethods":true},{"allDeclaredConstructors":true,"name":"io.quarkus.runtime.configuration.MemorySizeConverter","queriedMethods":[{"parameterTypes":[],"name":"provider"}]},{"allDeclaredConstructors":true,"name":"io.quarkus.runtime.logging.LogRuntimeConfig$CleanupFilterConfig$$CMImpl","allDeclaredMethods":true},{"allDeclaredConstructors":true,"name":"io.quarkus.runtime.logging.LogRuntimeConfig$SocketConfig$$CMImpl","allDeclaredMethods":true},{"allDeclaredConstructors":true,"name":"io.quarkus.runtime.configuration.InetSocketAddressConverter","queriedMethods":[{"parameterTypes":[],"name":"provider"}]},{"allDeclaredConstructors":true,"name":"java.util.logging.Level","allDeclaredMethods":true},{"allDeclaredConstructors":true,"name":"org.jboss.logmanager.handlers.SocketHandler$Protocol","allDeclaredMethods":true},{"allDeclaredConstructors":true,"name":"io.quarkus.runtime.logging.LogRuntimeConfig$SyslogConfig$$CMImpl","allDeclaredMethods":true},{"allDeclaredConstructors":true,"name":"org.jboss.logmanager.handlers.SyslogHandler$Facility","allDeclaredMethods":true},{"allDeclaredConstructors":true,"name":"org.jboss.logmanager.handlers.SyslogHandler$Protocol","allDeclaredMethods":true},{"allDeclaredConstructors":true,"name":"org.jboss.logmanager.handlers.SyslogHandler$SyslogType","allDeclaredMethods":true},{"allDeclaredConstructors":true,"name":"io.quarkus.runtime.logging.LogRuntimeConfig$SyslogConfig$CountingFraming","allDeclaredMethods":true},{"allDeclaredConstructors":true,"name":"io.quarkus.runtime.shutdown.ShutdownConfig$$CMImpl","allDeclaredMethods":true},{"allDeclaredConstructors":true,"name":"io.quarkus.resteasy.reactive.server.runtime.ResteasyReactiveServerRuntimeConfig$$CMImpl","allDeclaredMethods":true},{"allDeclaredConstructors":true,"name":"io.quarkus.resteasy.reactive.server.runtime.ResteasyReactiveServerRuntimeConfig$MultipartConfigGroup$$CMImpl","allDeclaredMethods":true},{"allDeclaredConstructors":true,"name":"io.quarkus.resteasy.reactive.server.runtime.ResteasyReactiveServerRuntimeConfig$InputPartConfigGroup$$CMImpl","allDeclaredMethods":true},{"allDeclaredConstructors":true,"name":"io.quarkus.vertx.http.runtime.DefaultAuthConfig$$CMImpl","allDeclaredMethods":true},{"allDeclaredConstructors":true,"name":"io.quarkus.vertx.http.runtime.DefaultAuthConfig$Defaults$$CMImpl","allDeclaredMethods":true},{"allDeclaredConstructors":true,"name":"io.quarkus.vertx.http.runtime.AuthRuntimeConfig$$CMImpl","allDeclaredMethods":true},{"allDeclaredConstructors":true,"name":"java.nio.file.Path","allDeclaredMethods":true},{"allDeclaredConstructors":true,"name":"io.quarkus.vertx.http.runtime.AuthRuntimeConfig$InclusiveMode","allDeclaredMethods":true},{"allDeclaredConstructors":true,"name":"io.quarkus.vertx.http.runtime.FormAuthConfig$$CMImpl","allDeclaredMethods":true},{"allDeclaredConstructors":true,"name":"io.quarkus.vertx.http.runtime.FormAuthConfig$CookieSameSite","allDeclaredMethods":true},{"allDeclaredConstructors":true,"name":"io.quarkus.runtime.configuration.TrimmedStringConverter"},{"allDeclaredConstructors":true,"name":"io.quarkus.vertx.http.runtime.PolicyMappingConfig$$CMImpl","allDeclaredMethods":true},{"allDeclaredConstructors":true,"name":"io.quarkus.vertx.http.runtime.PolicyMappingConfig$AppliesTo","allDeclaredMethods":true},{"allDeclaredConstructors":true,"name":"io.quarkus.vertx.http.runtime.PolicyConfig$$CMImpl","allDeclaredMethods":true},{"allDeclaredConstructors":true,"name":"io.quarkus.vertx.http.runtime.cors.CORSConfig$$CMImpl","allDeclaredMethods":true},{"allDeclaredConstructors":true,"name":"io.quarkus.vertx.http.runtime.VertxHttpConfig$$CMImpl","allDeclaredMethods":true},{"allDeclaredConstructors":true,"name":"io.quarkus.vertx.http.runtime.VertxHttpConfig$InsecureRequests","allDeclaredMethods":true},{"allDeclaredConstructors":true,"name":"io.quarkus.vertx.http.runtime.VertxHttpConfig$PayloadHint","allDeclaredMethods":true},{"allDeclaredConstructors":true,"name":"io.quarkus.vertx.http.runtime.AccessLogConfig$$CMImpl","allDeclaredMethods":true},{"allDeclaredConstructors":true,"name":"io.quarkus.vertx.http.runtime.BodyConfig$$CMImpl","allDeclaredMethods":true},{"allDeclaredConstructors":true,"name":"io.quarkus.vertx.http.runtime.MultiPartConfig$$CMImpl","allDeclaredMethods":true},{"allDeclaredConstructors":true,"name":"io.quarkus.vertx.http.runtime.FilterConfig$$CMImpl","allDeclaredMethods":true},{"allDeclaredConstructors":true,"name":"io.quarkus.vertx.http.runtime.HeaderConfig$$CMImpl","allDeclaredMethods":true},{"allDeclaredConstructors":true,"name":"io.quarkus.vertx.http.runtime.ServerLimitsConfig$$CMImpl","allDeclaredMethods":true},{"allDeclaredConstructors":true,"name":"java.util.OptionalLong","allDeclaredMethods":true},{"allDeclaredConstructors":true,"name":"io.quarkus.vertx.http.runtime.ProxyConfig$$CMImpl","allDeclaredMethods":true},{"allDeclaredConstructors":true,"name":"io.quarkus.vertx.http.runtime.ProxyConfig$ForwardedPrecedence","allDeclaredMethods":true},{"allDeclaredConstructors":true,"name":"io.quarkus.vertx.http.runtime.TrustedProxyCheckPartConverter","queriedMethods":[{"parameterTypes":[],"name":"provider"}]},{"allDeclaredConstructors":true,"name":"io.quarkus.vertx.http.runtime.SameSiteCookieConfig$$CMImpl","allDeclaredMethods":true},{"allDeclaredConstructors":true,"name":"io.vertx.core.http.CookieSameSite","allDeclaredMethods":true},{"allDeclaredConstructors":true,"name":"io.quarkus.vertx.http.runtime.ServerSslConfig$$CMImpl","allDeclaredMethods":true},{"allDeclaredConstructors":true,"name":"io.quarkus.vertx.http.runtime.CertificateConfig$$CMImpl","allDeclaredMethods":true},{"allDeclaredConstructors":true,"name":"io.quarkus.vertx.http.runtime.StaticResourcesConfig$$CMImpl","allDeclaredMethods":true},{"allDeclaredConstructors":true,"name":"io.quarkus.vertx.http.runtime.TrafficShapingConfig$$CMImpl","allDeclaredMethods":true},{"allDeclaredConstructors":true,"name":"io.quarkus.vertx.http.runtime.WebsocketServerConfig$$CMImpl","allDeclaredMethods":true},{"allDeclaredConstructors":true,"name":"io.quarkus.vertx.http.runtime.management.ManagementConfig$$CMImpl","allDeclaredMethods":true},{"allDeclaredConstructors":true,"name":"io.quarkus.vertx.http.runtime.management.ManagementRuntimeAuthConfig$$CMImpl","allDeclaredMethods":true},{"allDeclaredConstructors":true,"name":"io.quarkus.scheduler.runtime.SchedulerRuntimeConfig$$CMImpl","allDeclaredMethods":true},{"allDeclaredConstructors":true,"name":"io.quarkus.scheduler.runtime.SchedulerRuntimeConfig$StartMode","allDeclaredMethods":true},{"allDeclaredConstructors":true,"name":"io.quarkus.vertx.core.runtime.config.VertxConfiguration$$CMImpl","allDeclaredMethods":true},{"allDeclaredConstructors":true,"name":"io.quarkus.vertx.core.runtime.config.ClusterConfiguration$$CMImpl","allDeclaredMethods":true},{"allDeclaredConstructors":true,"name":"io.quarkus.vertx.core.runtime.config.EventBusConfiguration$$CMImpl","allDeclaredMethods":true},{"allDeclaredConstructors":true,"name":"io.quarkus.vertx.core.runtime.config.JksConfiguration$$CMImpl","allDeclaredMethods":true},{"allDeclaredConstructors":true,"name":"io.quarkus.vertx.core.runtime.config.PemKeyCertConfiguration$$CMImpl","allDeclaredMethods":true},{"allDeclaredConstructors":true,"name":"io.quarkus.vertx.core.runtime.config.PfxConfiguration$$CMImpl","allDeclaredMethods":true},{"allDeclaredConstructors":true,"name":"io.quarkus.vertx.core.runtime.config.PemTrustCertConfiguration$$CMImpl","allDeclaredMethods":true},{"allDeclaredConstructors":true,"name":"io.quarkus.vertx.core.runtime.config.AddressResolverConfiguration$$CMImpl","allDeclaredMethods":true},{"allDeclaredConstructors":true,"name":"io.quarkus.mailer.runtime.MailersRuntimeConfig$$CMImpl","allDeclaredMethods":true},{"allDeclaredConstructors":true,"name":"io.quarkus.mailer.runtime.MailerRuntimeConfig$$CMImpl","allDeclaredMethods":true},{"allDeclaredConstructors":true,"name":"io.quarkus.mailer.runtime.TrimmedPatternConverter","queriedMethods":[{"parameterTypes":[],"name":"provider"}]},{"allDeclaredConstructors":true,"name":"io.quarkus.mailer.runtime.DkimSignOptionsConfig$$CMImpl","allDeclaredMethods":true},{"allDeclaredConstructors":true,"name":"io.quarkus.mailer.runtime.DkimSignOptionsConfig$CanonicalizationAlgorithmOption","allDeclaredMethods":true},{"allDeclaredConstructors":true,"name":"io.quarkus.mailer.runtime.NtlmConfig$$CMImpl","allDeclaredMethods":true},{"allDeclaredConstructors":true,"name":"io.quarkus.mailer.runtime.TrustStoreConfig$$CMImpl","allDeclaredMethods":true},{"allDeclaredConstructors":true,"name":"io.quarkus.tls.runtime.config.TlsConfig$$CMImpl","allDeclaredMethods":true},{"allDeclaredConstructors":true,"name":"io.quarkus.tls.runtime.config.TlsBucketConfig$$CMImpl","allDeclaredMethods":true},{"allDeclaredConstructors":true,"name":"io.quarkus.tls.runtime.config.KeyStoreConfig$$CMImpl","allDeclaredMethods":true},{"allDeclaredConstructors":true,"name":"io.quarkus.tls.runtime.config.KeyStoreCredentialProviderConfig$$CMImpl","allDeclaredMethods":true},{"allDeclaredConstructors":true,"name":"io.quarkus.tls.runtime.config.JKSKeyStoreConfig$$CMImpl","allDeclaredMethods":true},{"allDeclaredConstructors":true,"name":"io.quarkus.tls.runtime.config.P12KeyStoreConfig$$CMImpl","allDeclaredMethods":true},{"allDeclaredConstructors":true,"name":"io.quarkus.tls.runtime.config.PemKeyCertConfig$$CMImpl","allDeclaredMethods":true},{"allDeclaredConstructors":true,"name":"io.quarkus.tls.runtime.config.PemKeyCertConfig$KeyCertConfig$$CMImpl","allDeclaredMethods":true},{"allDeclaredConstructors":true,"name":"io.quarkus.tls.runtime.config.TrustStoreConfig$$CMImpl","allDeclaredMethods":true},{"allDeclaredConstructors":true,"name":"io.quarkus.tls.runtime.config.TrustStoreConfig$CertificateExpiryPolicy","allDeclaredMethods":true},{"allDeclaredConstructors":true,"name":"io.quarkus.tls.runtime.config.TrustStoreCredentialProviderConfig$$CMImpl","allDeclaredMethods":true},{"allDeclaredConstructors":true,"name":"io.quarkus.tls.runtime.config.JKSTrustStoreConfig$$CMImpl","allDeclaredMethods":true},{"allDeclaredConstructors":true,"name":"io.quarkus.tls.runtime.config.P12TrustStoreConfig$$CMImpl","allDeclaredMethods":true},{"allDeclaredConstructors":true,"name":"io.quarkus.tls.runtime.config.PemCertsConfig$$CMImpl","allDeclaredMethods":true},{"allDeclaredConstructors":true,"name":"io.quarkus.qute.runtime.QuteRuntimeConfig$$CMImpl","allDeclaredMethods":true},{"allDeclaredConstructors":true,"name":"io.quarkus.qute.runtime.QuteRuntimeConfig$PropertyNotFoundStrategy","allDeclaredMethods":true},{"allDeclaredConstructors":true,"name":"io.quarkus.mongodb.runtime.MongoConfig$$CMImpl","allDeclaredMethods":true},{"allDeclaredConstructors":true,"name":"io.quarkus.mongodb.runtime.MongoClientConfig$$CMImpl","allDeclaredMethods":true},{"allDeclaredConstructors":true,"name":"io.quarkus.mongodb.runtime.MongoClientConfig$ReactiveTransportConfig","allDeclaredMethods":true},{"allDeclaredConstructors":true,"name":"org.bson.UuidRepresentation","allDeclaredMethods":true},{"allDeclaredConstructors":true,"name":"io.quarkus.mongodb.runtime.CredentialConfig$$CMImpl","allDeclaredMethods":true},{"allDeclaredConstructors":true,"name":"io.quarkus.mongodb.runtime.WriteConcernConfig$$CMImpl","allDeclaredMethods":true},{"allDeclaredConstructors":true,"name":"io.quarkus.narayana.jta.runtime.TransactionManagerConfiguration$$CMImpl","allDeclaredMethods":true},{"allDeclaredConstructors":true,"name":"io.quarkus.narayana.jta.runtime.TransactionManagerConfiguration$ObjectStoreConfig$$CMImpl","allDeclaredMethods":true},{"allDeclaredConstructors":true,"name":"io.quarkus.narayana.jta.runtime.ObjectStoreType","allDeclaredMethods":true},{"allDeclaredConstructors":true,"name":"io.quarkus.runtime.generated.BuildTimeRunTimeFixedConfigSourceBuilder"},{"name":"io.quarkus.scheduler.Scheduled$Never"},{"allDeclaredConstructors":true,"name":"service.cloud.request.clientRequest.notification.service.NotificationManager_ScheduledInvoker_processEmailQueue_1fefd19b7c6ee85a888e0980ec66de1edeab91ce","allDeclaredMethods":true,"allDeclaredFields":true},{"allDeclaredConstructors":true,"name":"io.quarkus.qute.runtime.extensions.NumberTemplateExtensions_Extension_ValueResolver_mod_bd066910099671b808afec3771a44518fddd2bc9"},{"allDeclaredConstructors":true,"name":"io.quarkus.qute.runtime.extensions.CollectionTemplateExtensions_Extension_ValueResolver_getByIndex_657afe9a25009c92a9bdafe71a002284cc5c15d2"},{"allDeclaredConstructors":true,"name":"io.quarkus.qute.runtime.extensions.StringTemplateExtensions_Namespace_Extension_ValueResolver_3442496b96dd01591a8cd44b1eec1368ab728aba_-10"},{"allDeclaredConstructors":true,"name":"io.quarkus.qute.runtime.extensions.OrOperatorTemplateExtensions_Extension_ValueResolver_or_8f1638f5c0cac882965cb238c12ac4185e0c98f6"},{"allDeclaredConstructors":true,"name":"io.quarkus.qute.runtime.extensions.CollectionTemplateExtensions_Extension_ValueResolver_get_61a55da54cd4263e9dff1c28f2ed031026e30ccf"},{"allDeclaredConstructors":true,"name":"io.quarkus.qute.runtime.extensions.NumberTemplateExtensions_Extension_ValueResolver_subtractFromInt_c4c2a444b875632d1f05e7e19edee263d5d3e57a"},{"allDeclaredConstructors":true,"name":"io.quarkus.qute.runtime.extensions.NumberTemplateExtensions_Extension_ValueResolver_addToInt_c4c2a444b875632d1f05e7e19edee263d5d3e57a"},{"allDeclaredConstructors":true,"name":"io.quarkus.qute.runtime.extensions.NumberTemplateExtensions_Extension_ValueResolver_addToLong_9c9ad703eaa32c6f532414cf5a53b74af8f4a460"},{"allDeclaredConstructors":true,"name":"io.quarkus.qute.runtime.extensions.NumberTemplateExtensions_Extension_ValueResolver_subtractFromInt_7960693d39b2f712668a26c75b53fda89da3fb49"},{"allDeclaredConstructors":true,"name":"io.quarkus.qute.runtime.extensions.CollectionTemplateExtensions_Extension_ValueResolver_take_61a55da54cd4263e9dff1c28f2ed031026e30ccf"},{"allDeclaredConstructors":true,"name":"io.quarkus.qute.runtime.extensions.ConfigTemplateExtensions_Namespace_Extension_ValueResolver_dfba7aade0868074c2861c98e2a9a92f3178a51b_6"},{"allDeclaredConstructors":true,"name":"io.quarkus.qute.runtime.extensions.ConfigTemplateExtensions_Namespace_Extension_ValueResolver_dfba7aade0868074c2861c98e2a9a92f3178a51b_7"},{"allDeclaredConstructors":true,"name":"io.quarkus.qute.runtime.extensions.StringTemplateExtensions_Namespace_Extension_ValueResolver_3442496b96dd01591a8cd44b1eec1368ab728aba_0"},{"allDeclaredConstructors":true,"name":"io.quarkus.qute.runtime.extensions.StringTemplateExtensions_Namespace_Extension_ValueResolver_3442496b96dd01591a8cd44b1eec1368ab728aba_1"},{"allDeclaredConstructors":true,"name":"io.quarkus.qute.runtime.extensions.StringTemplateExtensions_Namespace_Extension_ValueResolver_3442496b96dd01591a8cd44b1eec1368ab728aba_2"},{"allDeclaredConstructors":true,"name":"io.quarkus.qute.runtime.extensions.StringTemplateExtensions_Extension_ValueResolver_plus_e66c3354160ead5dcfb550a04f31e523bc4c1d8a"},{"allDeclaredConstructors":true,"name":"io.quarkus.qute.runtime.extensions.TimeTemplateExtensions_Extension_ValueResolver_format_20fff29d757fefef0946b2d3432680c31e8cb1e1"},{"allDeclaredConstructors":true,"name":"io.quarkus.qute.runtime.extensions.CollectionTemplateExtensions_Extension_ValueResolver_reversed_c79dcd7e0c0c2e87acbcdb6425088ca1593854ca"},{"allDeclaredConstructors":true,"name":"io.quarkus.qute.runtime.extensions.ConfigTemplateExtensions_Namespace_Extension_ValueResolver_dfba7aade0868074c2861c98e2a9a92f3178a51b_5"},{"allDeclaredConstructors":true,"name":"io.quarkus.qute.runtime.extensions.CollectionTemplateExtensions_Extension_ValueResolver_first_c79dcd7e0c0c2e87acbcdb6425088ca1593854ca"},{"allDeclaredConstructors":true,"name":"io.quarkus.qute.runtime.extensions.TimeTemplateExtensions_Extension_ValueResolver_format_751439945e2ab1b1668ce644124b107cc3b9867b"},{"allDeclaredConstructors":true,"name":"io.quarkus.qute.runtime.extensions.StringTemplateExtensions_Namespace_Extension_ValueResolver_3442496b96dd01591a8cd44b1eec1368ab728aba_-1"},{"allDeclaredConstructors":true,"name":"io.quarkus.qute.runtime.extensions.StringTemplateExtensions_Namespace_Extension_ValueResolver_3442496b96dd01591a8cd44b1eec1368ab728aba_3"},{"allDeclaredConstructors":true,"name":"io.quarkus.qute.runtime.extensions.MapTemplateExtensions_Extension_ValueResolver_get_bc0571c57a00283edd7750dce31b35b7894dab35"},{"allDeclaredConstructors":true,"name":"io.quarkus.qute.runtime.extensions.CollectionTemplateExtensions_Extension_ValueResolver_takeLast_61a55da54cd4263e9dff1c28f2ed031026e30ccf"},{"allDeclaredConstructors":true,"name":"io.quarkus.qute.runtime.extensions.StringTemplateExtensions_Namespace_Extension_ValueResolver_3442496b96dd01591a8cd44b1eec1368ab728aba_-2"},{"allDeclaredConstructors":true,"name":"io.quarkus.qute.runtime.extensions.TimeTemplateExtensions_Namespace_Extension_ValueResolver_714eea0f4c980736bde0065fe73f573487f08e3a_5"},{"allDeclaredConstructors":true,"name":"io.quarkus.qute.runtime.extensions.CollectionTemplateExtensions_Extension_ValueResolver_last_c79dcd7e0c0c2e87acbcdb6425088ca1593854ca"},{"allDeclaredConstructors":true,"name":"io.quarkus.qute.runtime.extensions.MapTemplateExtensions_Extension_ValueResolver_containsKey_c312eb3fc6948f9b67e43528a7682ca853ccafa2"},{"allDeclaredConstructors":true,"name":"io.quarkus.qute.runtime.extensions.NumberTemplateExtensions_Extension_ValueResolver_addToLong_b00a071e584486616d898c53585494d0942de97d"},{"allDeclaredConstructors":true,"name":"io.quarkus.qute.runtime.extensions.NumberTemplateExtensions_Extension_ValueResolver_subtractFromLong_9c9ad703eaa32c6f532414cf5a53b74af8f4a460"},{"allDeclaredConstructors":true,"name":"io.quarkus.qute.runtime.extensions.MapTemplateExtensions_Extension_ValueResolver_map_2916869ff3e33525b6b33460e43bcf5d56e2e69c"},{"allDeclaredConstructors":true,"name":"io.quarkus.qute.runtime.extensions.ObjectsTemplateExtensions_Extension_ValueResolver_eq_4ef3e9d546711498e5ea229da4d3b2ee7e77ce15"},{"allDeclaredConstructors":true,"name":"io.quarkus.qute.runtime.extensions.StringTemplateExtensions_Extension_ValueResolver_fmtInstance_0e0c8527d491c736ae8021d28078331a20315a36"},{"allDeclaredConstructors":true,"name":"io.quarkus.qute.runtime.extensions.StringTemplateExtensions_Extension_ValueResolver_fmtInstance_6f657fb2a556a9885d398f282d9ed1dab1b37921"},{"allDeclaredConstructors":true,"name":"io.quarkus.qute.runtime.extensions.CollectionTemplateExtensions_Extension_ValueResolver_orEmpty_49cd7d5d995da0ed2a0b410e1718aafcfdfbec2b"},{"allDeclaredConstructors":true,"name":"io.quarkus.qute.runtime.extensions.TimeTemplateExtensions_Extension_ValueResolver_format_9d2fa65ff1dc33288b60815fc775a809a8f911d2"},{"allDeclaredConstructors":true,"name":"io.quarkus.qute.runtime.extensions.StringTemplateExtensions_Extension_ValueResolver_plus_6966d857ae4e63e2c007193192804f359f04d3e8"},{"allDeclaredConstructors":true,"name":"io.quarkus.qute.runtime.extensions.NumberTemplateExtensions_Extension_ValueResolver_subtractFromLong_b00a071e584486616d898c53585494d0942de97d"},{"allDeclaredConstructors":true,"name":"io.quarkus.qute.runtime.extensions.NumberTemplateExtensions_Extension_ValueResolver_addToInt_7960693d39b2f712668a26c75b53fda89da3fb49"},{"allDeclaredConstructors":true,"name":"io.quarkus.runtime.configuration.CidrAddressConverter","queriedMethods":[{"parameterTypes":[],"name":"provider"}]},{"allDeclaredConstructors":true,"name":"io.quarkus.runtime.configuration.InetAddressConverter","queriedMethods":[{"parameterTypes":[],"name":"provider"}]},{"allDeclaredConstructors":true,"name":"io.quarkus.runtime.configuration.RegexConverter","queriedMethods":[{"parameterTypes":[],"name":"provider"}]},{"allDeclaredConstructors":true,"name":"io.quarkus.runtime.configuration.PathConverter","queriedMethods":[{"parameterTypes":[],"name":"provider"}]},{"allDeclaredConstructors":true,"name":"io.quarkus.runtime.configuration.DurationConverter","queriedMethods":[{"parameterTypes":[],"name":"provider"}]},{"allDeclaredConstructors":true,"name":"io.quarkus.runtime.configuration.LocaleConverter","queriedMethods":[{"parameterTypes":[],"name":"provider"}]},{"allDeclaredConstructors":true,"name":"io.quarkus.runtime.configuration.ZoneIdConverter","queriedMethods":[{"parameterTypes":[],"name":"provider"}]},{"allDeclaredConstructors":true,"name":"io.quarkus.runtime.logging.InheritableLevelConverter","queriedMethods":[{"parameterTypes":[],"name":"provider"}]},{"allDeclaredConstructors":true,"name":"io.smallrye.config.source.yaml.YamlConfigSourceLoader$InClassPath"},{"allDeclaredConstructors":true,"name":"io.smallrye.config.source.yaml.YamlConfigSourceLoader$InFileSystem"},{"allDeclaredConstructors":true,"name":"io.smallrye.config.source.yaml.YamlLocationConfigSourceFactory"},{"allDeclaredConstructors":true,"name":"io.smallrye.config.PropertiesLocationConfigSourceFactory"},{"allDeclaredConstructors":true,"name":"io.quarkus.runtime.generated.StaticInitConfig"},{"allDeclaredConstructors":true,"name":"io.quarkus.runtime.generated.RunTimeConfig"},{"allDeclaredConstructors":true,"name":"jakarta.enterprise.inject.Any","allDeclaredMethods":true},{"allDeclaredConstructors":true,"name":"io.quarkus.virtual.threads.VirtualThreads","allDeclaredMethods":true},{"allDeclaredConstructors":true,"name":"jakarta.enterprise.context.BeforeDestroyed","allDeclaredMethods":true},{"allDeclaredConstructors":true,"name":"io.quarkus.netty.MainEventLoopGroup","allDeclaredMethods":true},{"allDeclaredConstructors":true,"name":"jakarta.enterprise.inject.Default","allDeclaredMethods":true},{"allDeclaredConstructors":true,"name":"io.quarkus.arc.log.LoggerName","allDeclaredMethods":true},{"allDeclaredConstructors":true,"name":"jakarta.enterprise.inject.Decorated","allDeclaredMethods":true},{"allDeclaredConstructors":true,"name":"io.quarkus.qute.Location","allDeclaredMethods":true},{"allDeclaredConstructors":true,"name":"io.quarkus.mongodb.MongoClientName","allDeclaredMethods":true},{"allDeclaredConstructors":true,"name":"io.quarkus.runtime.annotations.CommandLineArguments","allDeclaredMethods":true},{"allDeclaredConstructors":true,"name":"io.smallrye.context.api.NamedInstance","allDeclaredMethods":true},{"allDeclaredConstructors":true,"name":"io.quarkus.arc.All","allDeclaredMethods":true},{"allDeclaredConstructors":true,"name":"jakarta.enterprise.inject.Intercepted","allDeclaredMethods":true},{"allDeclaredConstructors":true,"name":"io.quarkus.netty.BossEventLoopGroup","allDeclaredMethods":true},{"allDeclaredConstructors":true,"name":"org.eclipse.microprofile.config.inject.ConfigProperty","allDeclaredMethods":true},{"allDeclaredConstructors":true,"name":"jakarta.enterprise.context.Initialized","allDeclaredMethods":true},{"allDeclaredConstructors":true,"name":"io.quarkus.mailer.MailerName","allDeclaredMethods":true},{"allDeclaredConstructors":true,"name":"io.quarkus.qute.i18n.Localized","allDeclaredMethods":true},{"allDeclaredConstructors":true,"name":"org.eclipse.microprofile.config.inject.ConfigProperties","allDeclaredMethods":true},{"allDeclaredConstructors":true,"name":"jakarta.enterprise.context.Destroyed","allDeclaredMethods":true},{"allDeclaredConstructors":true,"name":"io.quarkus.arc.impl.Identified","allDeclaredMethods":true},{"allDeclaredConstructors":true,"name":"io.smallrye.common.annotation.Identifier","allDeclaredMethods":true},{"allDeclaredConstructors":true,"name":"jakarta.inject.Named","allDeclaredMethods":true},{"allDeclaredConstructors":true,"name":"io.quarkus.vertx.SafeVertxContext","allDeclaredMethods":true},{"allDeclaredConstructors":true,"name":"jakarta.enterprise.context.control.ActivateRequestContext","allDeclaredMethods":true},{"allDeclaredConstructors":true,"name":"io.quarkus.arc.Lock","allDeclaredMethods":true},{"allDeclaredConstructors":true,"name":"io.smallrye.context.api.CurrentThreadContext","allDeclaredMethods":true},{"allDeclaredConstructors":true,"name":"jakarta.transaction.Transactional","allDeclaredMethods":true},{"allDeclaredConstructors":true,"name":"io.quarkus.arc.runtime.ConfigStaticInitCheck","allDeclaredMethods":true},{"allDeclaredConstructors":true,"name":"org.jboss.resteasy.reactive.server.vertx.serializers.ServerVertxBufferMessageBodyWriter"},{"allDeclaredConstructors":true,"name":"org.jboss.resteasy.reactive.server.vertx.serializers.ServerMutinyBufferMessageBodyWriter"},{"allDeclaredConstructors":true,"name":"org.jboss.resteasy.reactive.server.vertx.serializers.ServerVertxAsyncFileMessageBodyWriter"},{"allDeclaredConstructors":true,"name":"org.jboss.resteasy.reactive.server.vertx.serializers.ServerMutinyAsyncFileMessageBodyWriter"},{"allDeclaredConstructors":true,"name":"io.quarkus.resteasy.reactive.jackson.runtime.serialisers.BasicServerJacksonMessageBodyWriter"},{"allDeclaredConstructors":true,"name":"io.quarkus.resteasy.reactive.jackson.runtime.serialisers.vertx.VertxJsonArrayMessageBodyWriter"},{"allDeclaredConstructors":true,"name":"io.quarkus.resteasy.reactive.jackson.runtime.serialisers.vertx.VertxJsonObjectMessageBodyWriter"},{"allDeclaredConstructors":true,"name":"io.quarkus.resteasy.reactive.server.runtime.QuarkusServerPathBodyHandler"},{"allDeclaredConstructors":true,"name":"io.quarkus.resteasy.reactive.jackson.runtime.serialisers.ServerJacksonMessageBodyReader"},{"allDeclaredConstructors":true,"name":"io.quarkus.resteasy.reactive.jackson.runtime.serialisers.vertx.VertxJsonArrayMessageBodyReader"},{"allDeclaredConstructors":true,"name":"io.quarkus.resteasy.reactive.jackson.runtime.serialisers.vertx.VertxJsonObjectMessageBodyReader"},{"allDeclaredConstructors":true,"name":"org.jboss.resteasy.reactive.server.providers.serialisers.ServerStringMessageBodyHandler"},{"allDeclaredConstructors":true,"name":"org.jboss.resteasy.reactive.server.providers.serialisers.ServerCharArrayMessageBodyHandler"},{"allDeclaredConstructors":true,"name":"org.jboss.resteasy.reactive.server.providers.serialisers.ServerByteArrayMessageBodyHandler"},{"allDeclaredConstructors":true,"name":"org.jboss.resteasy.reactive.server.providers.serialisers.ServerFormUrlEncodedProvider"},{"allDeclaredConstructors":true,"name":"org.jboss.resteasy.reactive.server.providers.serialisers.ServerInputStreamMessageBodyHandler"},{"allDeclaredConstructors":true,"name":"org.jboss.resteasy.reactive.server.providers.serialisers.StreamingOutputMessageBodyWriter"},{"allDeclaredConstructors":true,"name":"org.jboss.resteasy.reactive.server.providers.serialisers.ServerReaderBodyHandler"},{"allDeclaredConstructors":true,"name":"org.jboss.resteasy.reactive.server.providers.serialisers.ServerFileBodyHandler"},{"allDeclaredConstructors":true,"name":"org.jboss.resteasy.reactive.server.providers.serialisers.ServerFilePartBodyHandler"},{"allDeclaredConstructors":true,"name":"org.jboss.resteasy.reactive.server.core.multipart.MultipartMessageBodyWriter"},{"allDeclaredConstructors":true,"name":"org.jboss.resteasy.reactive.server.providers.serialisers.ServerPathBodyHandler"},{"allDeclaredConstructors":true,"name":"org.jboss.resteasy.reactive.server.providers.serialisers.ServerPathPartBodyHandler"},{"allDeclaredConstructors":true,"name":"org.jboss.resteasy.reactive.server.providers.serialisers.ServerBooleanMessageBodyHandler"},{"allDeclaredConstructors":true,"name":"org.jboss.resteasy.reactive.server.providers.serialisers.ServerCharacterMessageBodyHandler"},{"allDeclaredConstructors":true,"name":"org.jboss.resteasy.reactive.server.providers.serialisers.ServerNumberMessageBodyHandler"},{"allDeclaredConstructors":true,"name":"io.quarkus.resteasy.reactive.server.runtime.QuarkusServerFileBodyHandler"},{"allDeclaredConstructors":true,"name":"org.jboss.resteasy.reactive.server.providers.serialisers.ServerDefaultTextPlainBodyHandler"},{"allDeclaredClasses":true,"allDeclaredConstructors":true,"name":"service.cloud.request.clientRequest.estela.dto.FileRequestDTO","allDeclaredMethods":true,"allDeclaredFields":true},{"name":"java.nio.Bits","fields":[{"name":"MAX_MEMORY"},{"name":"UNALIGNED"},{"name":"UNSAFE_SET_THRESHOLD"}]},{"name":"io.quarkus.jackson.runtime.ConfigurationCustomizer","fields":[{"name":"jacksonBuildTimeConfig"}]},{"name":"io.quarkus.qute.runtime.ContentTypes","fields":[{"name":"config"}]},{"name":"service.cloud.request.clientRequest.config.ApplicationProperties","fields":[{"name":"urlBizlinks"},{"name":"urlEstela"},{"name":"ambiente"},{"name":"rutaBaseDocConfig"},{"name":"urlSunatEmision"},{"name":"rutaBaseDocAnexos"},{"name":"keystoreCertificateType"},{"name":"supplierCertificate"},{"name":"urlOse"},{"name":"urlSunatRetencion"},{"name":"urlSunatConsulta"}]},{"methods":[{"parameterTypes":["java.lang.String","long"],"name":"name"}],"name":"java.lang.Thread$Builder$OfVirtual"},{"methods":[{"parameterTypes":[],"name":"factory"}],"name":"java.lang.Thread$Builder"},{"methods":[{"parameterTypes":["java.security.SecureRandomParameters"],"name":"<init>"}],"name":"sun.security.provider.NativePRNG"},{"methods":[{"parameterTypes":[],"name":"getUnsafe"},{"parameterTypes":["java.lang.Class","int"],"name":"allocateUninitializedArray"}],"name":"jdk.internal.misc.Unsafe"},{"methods":[{"parameterTypes":["long","long"],"name":"<init>"}],"name":"java.nio.DirectByteBuffer"},{"methods":[{"parameterTypes":["io.vertx.core.Vertx","io.vertx.mutiny.core.Vertx","io.quarkus.mailer.runtime.MailersRuntimeConfig","io.quarkus.runtime.LaunchMode","io.quarkus.mailer.runtime.MailerSupport","io.quarkus.tls.TlsConfigurationRegistry","jakarta.enterprise.event.Event"],"name":"<init>"}],"name":"io.quarkus.mailer.runtime.Mailers"},{"methods":[{"parameterTypes":["jakarta.transaction.UserTransaction","jakarta.transaction.TransactionManager","io.quarkus.narayana.jta.runtime.TransactionManagerConfiguration"],"name":"<init>"}],"name":"io.quarkus.narayana.jta.RequestScopedTransaction"},{"methods":[{"parameterTypes":["io.quarkus.scheduler.common.runtime.SchedulerContext","io.quarkus.scheduler.runtime.SchedulerRuntimeConfig","jakarta.enterprise.event.Event","jakarta.enterprise.event.Event","jakarta.enterprise.event.Event","jakarta.enterprise.event.Event","jakarta.enterprise.event.Event","jakarta.enterprise.event.Event","jakarta.enterprise.event.Event","jakarta.enterprise.event.Event","io.vertx.core.Vertx","io.quarkus.scheduler.runtime.SchedulerConfig","jakarta.enterprise.inject.Instance","java.util.concurrent.ScheduledExecutorService"],"name":"<init>"}],"name":"io.quarkus.scheduler.runtime.SimpleScheduler"},{"methods":[{"parameterTypes":["io.quarkus.mongodb.runtime.MongoConfig","io.quarkus.mongodb.runtime.MongoClientSupport","jakarta.enterprise.inject.Instance","io.quarkus.tls.TlsConfigurationRegistry","jakarta.enterprise.inject.Instance","jakarta.enterprise.inject.Instance","jakarta.enterprise.inject.Instance","jakarta.enterprise.inject.Instance","io.vertx.core.Vertx"],"name":"<init>"}],"name":"io.quarkus.mongodb.runtime.MongoClients"},{"methods":[{"parameterTypes":[],"name":"<init>"}],"name":"io.quarkus.qute.i18n.MessageBundles"},{"methods":[{"parameterTypes":["io.quarkus.qute.runtime.QuteRecorder$QuteContext","io.quarkus.qute.runtime.QuteConfig","io.quarkus.qute.runtime.QuteRuntimeConfig","jakarta.enterprise.event.Event","jakarta.enterprise.event.Event","io.quarkus.qute.runtime.ContentTypes","io.quarkus.runtime.LaunchMode","io.quarkus.runtime.LocalesBuildTimeConfig","java.util.List","java.util.List","java.util.List","java.util.List","java.util.List"],"name":"<init>"}],"name":"io.quarkus.qute.runtime.EngineProducer"},{"methods":[{"parameterTypes":["java.lang.String"],"name":"mongoClient"}],"name":"service.cloud.request.clientRequest.config.MongoClientProducer"},{"methods":[{"parameterTypes":[],"name":"<init>"}],"name":"io.quarkus.arc.generator.Default_jakarta_enterprise_context_ApplicationScoped_ContextInstances"},{"methods":[{"parameterTypes":["java.util.List"],"name":"getTaxTotalValueV21"},{"parameterTypes":["java.util.Date"],"name":"formatDueDate"},{"parameterTypes":["java.util.List","java.lang.String"],"name":"getTaxTotalValue2"},{"parameterTypes":["service.cloud.request.clientRequest.xmlFormatSunat.xsd.commonaggregatecomponents_2.AddressType"],"name":"formatDepProvDist"},{"parameterTypes":["java.util.List"],"name":"getDiscountItem"},{"parameterTypes":["java.lang.String","java.lang.String","int","int","int"],"name":"generatePDF417Code"},{"parameterTypes":["java.util.List","java.lang.String"],"name":"getSubtotalValueFromTransaction"},{"parameterTypes":["service.cloud.request.clientRequest.xmlFormatSunat.xsd.commonextensioncomponents_2.UBLExtensionsType"],"name":"generateDigestValue"},{"parameterTypes":["java.util.List","java.lang.String"],"name":"getTaxTotalValue"},{"parameterTypes":["java.util.List","java.lang.String"],"name":"getTransaccionTotales"},{"parameterTypes":["java.util.List","java.lang.String"],"name":"getPricingReferenceValue"},{"parameterTypes":["java.math.BigDecimal","java.lang.String"],"name":"getCurrency"},{"parameterTypes":["java.lang.String","java.lang.String","java.lang.String","java.lang.String","java.util.List","java.lang.String","java.lang.String","java.lang.String","java.lang.String","service.cloud.request.clientRequest.xmlFormatSunat.xsd.commonextensioncomponents_2.UBLExtensionsType"],"name":"generateBarCodeInfoString"},{"parameterTypes":["service.cloud.request.clientRequest.xmlFormatSunat.xsd.commonextensioncomponents_2.UBLExtensionsType"],"name":"getSignatureValue"},{"parameterTypes":["java.util.Map"],"name":"getLegendList"},{"parameterTypes":["java.lang.String","java.lang.String","java.lang.String","java.math.BigDecimal","java.math.BigDecimal","service.cloud.request.clientRequest.xmlFormatSunat.xsd.commonaggregatecomponents_2.SupplierPartyType","service.cloud.request.clientRequest.xmlFormatSunat.xsd.commonaggregatecomponents_2.CustomerPartyType","service.cloud.request.clientRequest.xmlFormatSunat.xsd.commonextensioncomponents_2.UBLExtensionsType"],"name":"generateGuiaBarcodeInfoV2"},{"parameterTypes":["java.util.List","java.lang.String"],"name":"getContractDocumentReference"},{"parameterTypes":["java.math.BigDecimal","java.lang.String"],"name":"getCurrencyV3"},{"parameterTypes":["java.util.List"],"name":"getSunatTransactionInfo"},{"parameterTypes":["java.util.List"],"name":"getRemissionGuides"},{"parameterTypes":["java.util.List"],"name":"getaddLeyends"},{"parameterTypes":["service.cloud.request.clientRequest.xmlFormatSunat.xsd.commonaggregatecomponents_2.BillingReferenceType"],"name":"getDocumentReferenceValue"},{"parameterTypes":["service.cloud.request.clientRequest.xmlFormatSunat.xsd.commonextensioncomponents_2.UBLExtensionsType"],"name":"getDigestValue"}],"name":"service.cloud.request.clientRequest.handler.refactorPdf.service.impl.BaseDocumentService"},{"methods":[{"parameterTypes":["jakarta.ws.rs.core.MediaType","java.lang.Class"],"name":"isReadable"}],"name":"org.jboss.resteasy.reactive.common.providers.serialisers.AbstractJsonMessageBodyReader"},{"methods":[{"parameterTypes":["jakarta.enterprise.inject.spi.InjectionPoint"],"name":"producesListConfigProperty"},{"parameterTypes":["jakarta.enterprise.inject.spi.InjectionPoint"],"name":"produceOptionalIntConfigProperty"},{"parameterTypes":["jakarta.enterprise.inject.spi.InjectionPoint"],"name":"produceFloatConfigProperty"},{"parameterTypes":["jakarta.enterprise.inject.spi.InjectionPoint"],"name":"produceOptionalDoubleConfigProperty"},{"parameterTypes":["jakarta.enterprise.inject.spi.InjectionPoint"],"name":"produceOptionalConfigProperty"},{"parameterTypes":["jakarta.enterprise.inject.spi.InjectionPoint"],"name":"producesSetConfigProperty"},{"parameterTypes":["jakarta.enterprise.inject.spi.InjectionPoint"],"name":"produceConfigValue"},{"parameterTypes":["jakarta.enterprise.inject.spi.InjectionPoint"],"name":"produceCharacterConfigProperty"},{"parameterTypes":["jakarta.enterprise.inject.spi.InjectionPoint"],"name":"getIntegerValue"},{"parameterTypes":["jakarta.enterprise.inject.spi.InjectionPoint"],"name":"getLongValue"},{"parameterTypes":["jakarta.enterprise.inject.spi.InjectionPoint"],"name":"produceBooleanConfigProperty"},{"parameterTypes":["jakarta.enterprise.inject.spi.InjectionPoint"],"name":"produceOptionalLongConfigProperty"},{"parameterTypes":["jakarta.enterprise.inject.spi.InjectionPoint"],"name":"produceStringConfigProperty"},{"parameterTypes":["jakarta.enterprise.inject.spi.InjectionPoint"],"name":"produceByteConfigProperty"},{"parameterTypes":["jakarta.enterprise.inject.spi.InjectionPoint"],"name":"producesMapConfigProperty"},{"parameterTypes":["jakarta.enterprise.inject.spi.InjectionPoint"],"name":"produceShortConfigProperty"},{"parameterTypes":["jakarta.enterprise.inject.spi.InjectionPoint"],"name":"produceDoubleConfigProperty"},{"parameterTypes":["jakarta.enterprise.inject.spi.InjectionPoint"],"name":"produceSupplierConfigProperty"}],"name":"io.smallrye.config.inject.ConfigProducer"},{"methods":[{"parameterTypes":[],"name":"<init>"}],"name":"io.quarkus.arc.generator.Default_jakarta_enterprise_context_RequestScoped_ContextInstances"},{"methods":[{"parameterTypes":[],"name":"<init>"}],"name":"io.smallrye.mutiny.streams.Engine","queriedMethods":[{"parameterTypes":[],"name":"provider"}]},{"methods":[{"parameterTypes":[],"name":"<init>"}],"name":"org.eclipse.microprofile.reactive.streams.operators.core.ReactiveStreamsFactoryImpl","queriedMethods":[{"parameterTypes":[],"name":"provider"}]},{"methods":[{"parameterTypes":[],"name":"<init>"}],"name":"io.quarkus.vertx.runtime.VertxNonBlockingProvider","queriedMethods":[{"parameterTypes":[],"name":"provider"}]},{"methods":[{"parameterTypes":[],"name":"<init>"}],"name":"org.jboss.resteasy.reactive.common.jaxrs.RuntimeDelegateImpl","queriedMethods":[{"parameterTypes":[],"name":"provider"}]},{"methods":[{"parameterTypes":[],"name":"<init>"}],"name":"org.eclipse.parsson.JsonProviderImpl","queriedMethods":[{"parameterTypes":[],"name":"provider"}]},{"methods":[{"parameterTypes":[],"name":"<init>"}],"name":"io.quarkus.vertx.http.runtime.attribute.RemoteIPAttribute$Builder","queriedMethods":[{"parameterTypes":[],"name":"provider"}]},{"methods":[{"parameterTypes":[],"name":"<init>"}],"name":"io.quarkus.vertx.http.runtime.attribute.LocalIPAttribute$Builder","queriedMethods":[{"parameterTypes":[],"name":"provider"}]},{"methods":[{"parameterTypes":[],"name":"<init>"}],"name":"io.quarkus.vertx.http.runtime.attribute.RequestProtocolAttribute$Builder","queriedMethods":[{"parameterTypes":[],"name":"provider"}]},{"methods":[{"parameterTypes":[],"name":"<init>"}],"name":"io.quarkus.vertx.http.runtime.attribute.LocalPortAttribute$Builder","queriedMethods":[{"parameterTypes":[],"name":"provider"}]},{"methods":[{"parameterTypes":[],"name":"<init>"}],"name":"io.quarkus.vertx.http.runtime.attribute.IdentUsernameAttribute$Builder","queriedMethods":[{"parameterTypes":[],"name":"provider"}]},{"methods":[{"parameterTypes":[],"name":"<init>"}],"name":"io.quarkus.vertx.http.runtime.attribute.RequestMethodAttribute$Builder","queriedMethods":[{"parameterTypes":[],"name":"provider"}]},{"methods":[{"parameterTypes":[],"name":"<init>"}],"name":"io.quarkus.vertx.http.runtime.attribute.QueryStringAttribute$Builder","queriedMethods":[{"parameterTypes":[],"name":"provider"}]},{"methods":[{"parameterTypes":[],"name":"<init>"}],"name":"io.quarkus.vertx.http.runtime.attribute.RequestLineAttribute$Builder","queriedMethods":[{"parameterTypes":[],"name":"provider"}]},{"methods":[{"parameterTypes":[],"name":"<init>"}],"name":"io.quarkus.vertx.http.runtime.attribute.BytesSentAttribute$Builder","queriedMethods":[{"parameterTypes":[],"name":"provider"}]},{"methods":[{"parameterTypes":[],"name":"<init>"}],"name":"io.quarkus.vertx.http.runtime.attribute.DateTimeAttribute$Builder","queriedMethods":[{"parameterTypes":[],"name":"provider"}]},{"methods":[{"parameterTypes":[],"name":"<init>"}],"name":"io.quarkus.vertx.http.runtime.attribute.RemoteUserAttribute$Builder","queriedMethods":[{"parameterTypes":[],"name":"provider"}]},{"methods":[{"parameterTypes":[],"name":"<init>"}],"name":"io.quarkus.vertx.http.runtime.attribute.RequestURLAttribute$Builder","queriedMethods":[{"parameterTypes":[],"name":"provider"}]},{"methods":[{"parameterTypes":[],"name":"<init>"}],"name":"io.quarkus.vertx.http.runtime.attribute.ThreadNameAttribute$Builder","queriedMethods":[{"parameterTypes":[],"name":"provider"}]},{"methods":[{"parameterTypes":[],"name":"<init>"}],"name":"io.quarkus.vertx.http.runtime.attribute.LocalServerNameAttribute$Builder","queriedMethods":[{"parameterTypes":[],"name":"provider"}]},{"methods":[{"parameterTypes":[],"name":"<init>"}],"name":"io.quarkus.vertx.http.runtime.attribute.RequestHeaderAttribute$Builder","queriedMethods":[{"parameterTypes":[],"name":"provider"}]},{"methods":[{"parameterTypes":[],"name":"<init>"}],"name":"io.quarkus.vertx.http.runtime.attribute.ResponseHeaderAttribute$Builder","queriedMethods":[{"parameterTypes":[],"name":"provider"}]},{"methods":[{"parameterTypes":[],"name":"<init>"}],"name":"io.quarkus.vertx.http.runtime.attribute.CookieAttribute$Builder","queriedMethods":[{"parameterTypes":[],"name":"provider"}]},{"methods":[{"parameterTypes":[],"name":"<init>"}],"name":"io.quarkus.vertx.http.runtime.attribute.ResponseCodeAttribute$Builder","queriedMethods":[{"parameterTypes":[],"name":"provider"}]},{"methods":[{"parameterTypes":[],"name":"<init>"}],"name":"io.quarkus.vertx.http.runtime.attribute.QueryParameterAttribute$Builder","queriedMethods":[{"parameterTypes":[],"name":"provider"}]},{"methods":[{"parameterTypes":[],"name":"<init>"}],"name":"io.quarkus.vertx.http.runtime.attribute.SslClientCertAttribute$Builder","queriedMethods":[{"parameterTypes":[],"name":"provider"}]},{"methods":[{"parameterTypes":[],"name":"<init>"}],"name":"io.quarkus.vertx.http.runtime.attribute.SslCipherAttribute$Builder","queriedMethods":[{"parameterTypes":[],"name":"provider"}]},{"methods":[{"parameterTypes":[],"name":"<init>"}],"name":"io.quarkus.vertx.http.runtime.attribute.SslSessionIdAttribute$Builder","queriedMethods":[{"parameterTypes":[],"name":"provider"}]},{"methods":[{"parameterTypes":[],"name":"<init>"}],"name":"io.quarkus.vertx.http.runtime.attribute.ResponseTimeAttribute$Builder","queriedMethods":[{"parameterTypes":[],"name":"provider"}]},{"methods":[{"parameterTypes":[],"name":"<init>"}],"name":"io.quarkus.vertx.http.runtime.attribute.TransportProtocolAttribute$Builder","queriedMethods":[{"parameterTypes":[],"name":"provider"}]},{"methods":[{"parameterTypes":[],"name":"<init>"}],"name":"io.quarkus.vertx.http.runtime.attribute.RequestSchemeAttribute$Builder","queriedMethods":[{"parameterTypes":[],"name":"provider"}]},{"methods":[{"parameterTypes":[],"name":"<init>"}],"name":"io.quarkus.vertx.http.runtime.attribute.SecureExchangeAttribute$Builder","queriedMethods":[{"parameterTypes":[],"name":"provider"}]},{"methods":[{"parameterTypes":[],"name":"<init>"}],"name":"io.quarkus.vertx.http.runtime.attribute.RemoteHostAttribute$Builder","queriedMethods":[{"parameterTypes":[],"name":"provider"}]},{"methods":[{"parameterTypes":[],"name":"<init>"}],"name":"io.quarkus.vertx.http.runtime.attribute.RequestPathAttribute$Builder","queriedMethods":[{"parameterTypes":[],"name":"provider"}]},{"methods":[{"parameterTypes":[],"name":"<init>"}],"name":"io.quarkus.vertx.http.runtime.attribute.NullAttribute$Builder","queriedMethods":[{"parameterTypes":[],"name":"provider"}]},{"methods":[{"parameterTypes":[],"name":"<init>"}],"name":"io.quarkus.vertx.http.runtime.attribute.AllRequestHeadersAttribute$Builder","queriedMethods":[{"parameterTypes":[],"name":"provider"}]},{"methods":[{"parameterTypes":[],"name":"<init>"}],"name":"io.quarkus.vertx.http.runtime.attribute.ExchangeDataAttribute$Builder","queriedMethods":[{"parameterTypes":[],"name":"provider"}]},{"methods":[{"parameterTypes":[],"name":"<init>"}],"name":"io.quarkus.vertx.http.runtime.attribute.VertxMDCDataAttribute$Builder","queriedMethods":[{"parameterTypes":[],"name":"provider"}]},{"methods":[{"parameterTypes":[],"name":"<init>"}],"name":"io.smallrye.config.SmallRyeConfigProviderResolver","queriedMethods":[{"parameterTypes":[],"name":"provider"}]},{"methods":[{"parameterTypes":[],"name":"<init>"}],"name":"io.quarkus.deployment.pkg.jar.JarTypeDefaultValueConfigInterceptor","queriedMethods":[{"parameterTypes":[],"name":"provider"}]},{"methods":[{"parameterTypes":[],"name":"<init>"}],"name":"io.quarkus.bootstrap.logging.InitialConfigurator","queriedMethods":[{"parameterTypes":[],"name":"provider"}]},{"methods":[{"parameterTypes":[],"name":"<init>"}],"name":"io.quarkus.vertx.runtime.jackson.QuarkusJacksonFactory","queriedMethods":[{"parameterTypes":[],"name":"provider"}]}]